MANIFEST.in
README.md
setup.cfg
setup.py
src/eWRT/__init__.py
src/eWRT.egg-info/PKG-INFO
src/eWRT.egg-info/SOURCES.txt
src/eWRT.egg-info/dependency_links.txt
src/eWRT.egg-info/requires.txt
src/eWRT.egg-info/top_level.txt
src/eWRT/access/__init__.py
src/eWRT/access/abstract_retrieve.py
src/eWRT/access/db.py
src/eWRT/access/file.py
src/eWRT/access/http.py
src/eWRT/access/javascript.py
src/eWRT/config/__init__.py
src/eWRT/input/__init__.py
src/eWRT/input/clean/__init__.py
src/eWRT/input/clean/text.py
src/eWRT/input/conv/__init__.py
src/eWRT/input/conv/doc.py
src/eWRT/input/conv/html.py
src/eWRT/input/conv/pdf.py
src/eWRT/input/conv/cxl/__init__.py
src/eWRT/input/corpus/__init__.py
src/eWRT/input/corpus/bbc/__init__.py
src/eWRT/input/corpus/reuters/__init__.py
src/eWRT/input/corpus/reuters/reuters.py
src/eWRT/input/csv/__init__.py
src/eWRT/input/csv/tests/__init__.py
src/eWRT/input/stock/__init__.py
src/eWRT/input/stock/data/__init__.py
src/eWRT/lib/Result.py
src/eWRT/lib/ResultSet.py
src/eWRT/lib/Webservice.py
src/eWRT/lib/__init__.py
src/eWRT/lib/apihelber.py
src/eWRT/lib/thirdparty/__init__.py
src/eWRT/lib/thirdparty/advas/__init__.py
src/eWRT/lib/thirdparty/advas/phonetics.py
src/eWRT/ontology/__init__.py
src/eWRT/ontology/compare/__init__.py
src/eWRT/ontology/compare/relations/__init__.py
src/eWRT/ontology/compare/relationtypes/__init__.py
src/eWRT/ontology/compare/terminology/__init__.py
src/eWRT/ontology/eval/__init__.py
src/eWRT/ontology/eval/terminology/__init__.py
src/eWRT/ontology/visualize/__init__.py
src/eWRT/stat/__init__.py
src/eWRT/stat/coherence/__init__.py
src/eWRT/stat/eval/__init__.py
src/eWRT/stat/eval/metrics.py
src/eWRT/stat/language/__init__.py
src/eWRT/stat/language/data/cs.csv
src/eWRT/stat/language/data/de.csv
src/eWRT/stat/language/data/en.csv
src/eWRT/stat/language/data/fr.csv
src/eWRT/stat/string/__init__.py
src/eWRT/stat/string/normalize.py
src/eWRT/stat/string/spelling.py
src/eWRT/util/__init__.py
src/eWRT/util/advLogging.py
src/eWRT/util/assert_return.py
src/eWRT/util/async.py
src/eWRT/util/cache.py
src/eWRT/util/exception.py
src/eWRT/util/execute.py
src/eWRT/util/loggerProfile.py
