Metadata-Version: 1.1
Name: eWRT
Version: 0.9.6.20180607
Summary: eWRT
Home-page: http://www.weblyzard.com/ewrt/
Author: Albert Weichselbraun, Heinz Lang, Gerhard Wohlgenannt, Johannes Duong, Norman Süsstrunk, Daniel Streiff
Author-email: albert@weblyzard.com, lang@weblyzard.com, wohlg@ai.wu.ac.at, johannes.duong@wu.ac.at, norman.suestrunk@htwchur.ch, daniel.streiff@htwchur.ch
License: GPL3
Platform: UNKNOWN
Classifier: Programming Language :: Python
Classifier: Programming Language :: Python :: 2
Classifier: Programming Language :: Python :: 2.7
